viasegura/__init__.py
viasegura/downloader.py
viasegura/labelers.py
viasegura/configs/__init__.py
viasegura/configs/config.json
viasegura/configs/config.py
viasegura/configs/lanenet_config.json
viasegura/utils/__init__.py
viasegura/utils/lanenet.py
viasegura-2.0.0.dist-info/LICENSE.md
viasegura-2.0.0.dist-info/METADATA
viasegura-2.0.0.dist-info/WHEEL
viasegura-2.0.0.dist-info/top_level.txt
viasegura-2.0.0.dist-info/RECORD
