Metadata-Version: 2.2
Name: viasegura
Version: 2.0.0
Summary: A python package to interact with Inter-American Development Bank machine learning models to automatic label elements for iRAP certification
Author: Jose Maria Marquez Blanco
Author-email: jose.marquez.blanco@gmail.com
Keywords: Machine Learning,safe road
Classifier: Development Status :: 3 - Alpha
Classifier: Operating System :: OS Independent
Classifier: Programming Language :: Python :: 3
Classifier: Programming Language :: Python :: 3.9
Classifier: Programming Language :: Python :: 3.10
Classifier: Programming Language :: Python :: 3.11
Classifier: Programming Language :: Python :: 3.12
Requires-Python: >=3.9
License-File: LICENSE.md
Requires-Dist: tensorflow
Requires-Dist: tf_keras
Requires-Dist: tqdm
Requires-Dist: boto3>=1.14.37
Requires-Dist: opencv-python>=4.2.0.34
Requires-Dist: scipy>=1.4.1
Requires-Dist: joblib
Requires-Dist: pandas>=1.0.3
Requires-Dist: numpy<2.0.0
Requires-Dist: pynmea2>=1.15.0
Requires-Dist: shapely
Requires-Dist: pillow==10.3.0
Dynamic: author
Dynamic: author-email
Dynamic: classifier
Dynamic: description
Dynamic: description-content-type
Dynamic: keywords
Dynamic: requires-dist
Dynamic: requires-python
Dynamic: summary
